{"dados": { 
    "data" : ["01/Mai", "02/Mai", "03/Mai", "04/Mai", "05/Mai", "06/Mai", "07/Mai", "08/Mai", "09/Mai", "10/Mai", "11/Mai", "12/Mai", "13/Mai", "14/Mai", "15/Mai", "16/Mai", "17/Mai", "18/Mai", "19/Mai", "20/Mai", "21/Mai", "22/Mai", "23/Mai", "24/Mai", "25/Mai", "26/Mai", "27/Mai", "28/Mai", "29/Mai", "30/Mai", "31/Mai", "01/Jun", "02/Jun", "03/Jun", "04/Jun", "05/Jun"],
"casosNovos" : [1, 0, 0, 0, 0, 0, 0, 0, 0, 0, 1, 0, 0, 0, 1, 0, 0, 4, 0, 0, 0, 2, 2, 1, 7, 8, 11, 3, 2, 1, 5, 4, 8, 8, 9, 5],
"recuperadosNovos" : [0, 0, 0, 0, 0, 0, 0, 0, 0, 0, 1, 0, 0, 0, 0, 0, 0, 0, 1, 0, 0, 0, 0, 2, 2, 2, 2, 3, 6, 2, 3, 2, 8, 5, 9, 3, 3],
"obitosNovos" : [0, 0, 0, 0, 0, 0, 0, 0, 0, 0, 0, 0, 0, 0, 0, 0, 0, 0, 0, 0, 0, 0, 0, 0, 0, 0, 0, 0, 0, 0, 0, 0, 0, 0, 0, 2, 1]
}
}
